odp/dataset.py
odp/new_client.py
odp/catalog_v2/__init__.py
odp/catalog_v2/catalog.py
odp/client/__init__.py
odp/client/auth.py
odp/tabular_v2/__init__.py
odp/tabular_v2/client/__init__.py
odp/tabular_v2/client/table.py
odp/tabular_v2/client/table_cursor.py
odp/tabular_v2/client/table_raw.py
odp/tabular_v2/client/table_stats.py
odp/tabular_v2/client/table_tx.py
odp/tabular_v2/client/validation.py
odp/tabular_v2/util/__init__.py
odp/tabular_v2/util/geo_conversion.py
odp/tabular_v2/util/iter2reader.py
odp/tabular_v2/util/vars_conversion.py
odp/tabular_v2/util/writebuffer.py
odp/util/__init__.py
odp/util/check_version.py
odp/util/cheapdantic/__init__.py
odp/util/cheapdantic/cheapdantic.py
odp_sdk/__init__.py
odp_sdk-0.28.7.dist-info/METADATA
odp_sdk-0.28.7.dist-info/WHEEL
odp_sdk-0.28.7.dist-info/RECORD
