Metadata-Version: 2.4
Name: odp-sdk
Version: 0.28.7
Summary: ODP Python SDK
Author-email: Thomas Li Fredriksen <thomas.fredriksen@oceandata.earth>
License-Expression: MIT
Requires-Python: <4,>=3.9.5
Requires-Dist: cryptography<45,>=44.0.1
Requires-Dist: geopandas<1.1,>=0.14
Requires-Dist: msal-extensions<2,>=1.1.0
Requires-Dist: msal<2,>=1.24.1
Requires-Dist: pandas<3,>=2.1.4
Requires-Dist: pyarrow<19,>=18.1.0
Requires-Dist: pyjwt<3,>=2.6.0
Requires-Dist: shapely<3,>=2.0.7
